odoo/addons/l10n_it_account_stamp_sale/README.rst
odoo/addons/l10n_it_account_stamp_sale/__init__.py
odoo/addons/l10n_it_account_stamp_sale/__manifest__.py
odoo/addons/l10n_it_account_stamp_sale/i18n/l10n_it_account_stamp_sale.pot
odoo/addons/l10n_it_account_stamp_sale/models/__init__.py
odoo/addons/l10n_it_account_stamp_sale/models/sale_order.py
odoo/addons/l10n_it_account_stamp_sale/readme/CONTRIBUTORS.rst
odoo/addons/l10n_it_account_stamp_sale/readme/DESCRIPTION.rst
odoo/addons/l10n_it_account_stamp_sale/static/description/icon.png
odoo/addons/l10n_it_account_stamp_sale/static/description/index.html
odoo12_addon_l10n_it_account_stamp_sale-12.0.1.0.2.dist-info/METADATA
odoo12_addon_l10n_it_account_stamp_sale-12.0.1.0.2.dist-info/WHEEL
odoo12_addon_l10n_it_account_stamp_sale-12.0.1.0.2.dist-info/top_level.txt
odoo12_addon_l10n_it_account_stamp_sale-12.0.1.0.2.dist-info/RECORD
